setup.py
dolphin/__init__.py
dolphin/configuration_dolphin.py
dolphin/context_encoder.py
dolphin/modeling_dolphin.py
nexaai_dolphin.egg-info/PKG-INFO
nexaai_dolphin.egg-info/SOURCES.txt
nexaai_dolphin.egg-info/dependency_links.txt
nexaai_dolphin.egg-info/requires.txt
nexaai_dolphin.egg-info/top_level.txt