Metadata-Version: 2.1
Name: nexaai-dolphin
Version: 0.0.1
Summary: A package for the Dolphin model under the Nexa AI framework
Home-page: https://github.com/NexaAI/nexa-dolphin
Author: Alex Chen, Zack Li
Author-email: octopus@nexa4ai.com
Keywords: nexa ai dolphin model machine-learning
Classifier: Development Status :: 3 - Alpha
Classifier: Intended Audience :: Developers
Classifier: Topic :: Scientific/Engineering :: Artificial Intelligence
Classifier: License :: OSI Approved :: MIT License
Classifier: Programming Language :: Python :: 3
Classifier: Programming Language :: Python :: 3.6
Classifier: Programming Language :: Python :: 3.7
Classifier: Programming Language :: Python :: 3.8
Classifier: Programming Language :: Python :: 3.9
Classifier: Programming Language :: Python :: 3.10
Classifier: Operating System :: OS Independent
Requires-Python: >=3.6
Requires-Dist: transformers
Requires-Dist: torch
